LICENSE
MANIFEST.in
README.md
package.json
setup.py
dash_heatmap/DashHeatmap.py
dash_heatmap/__init__.py
dash_heatmap/_imports_.py
dash_heatmap/button.py
dash_heatmap/controls.py
dash_heatmap/dash_heatmap.min.js
dash_heatmap/dash_heatmap.min.js.map
dash_heatmap/fetchData.py
dash_heatmap/heatmap.py
dash_heatmap/initHeatmap.py
dash_heatmap/mapKey.py
dash_heatmap/metadata.json
dash_heatmap/package-info.json
dash_heatmap/svgControls.py
dash_heatmap.egg-info/PKG-INFO
dash_heatmap.egg-info/SOURCES.txt
dash_heatmap.egg-info/dependency_links.txt
dash_heatmap.egg-info/top_level.txt