Metadata-Version: 1.1
Name: dash-heatmap
Version: 0.0.1
Summary: Warehouse product moves heatmap
Home-page: UNKNOWN
Author: Richard Whitefoot <richard.whitefoot@unipart.io>
Author-email: UNKNOWN
License: GPL-3.0
Platform: UNKNOWN
Classifier: Framework :: Dash
